xdgpspconf/__about__.py
xdgpspconf/__init__.py
xdgpspconf/__main__.py
xdgpspconf/base.py
xdgpspconf/command_line.py
xdgpspconf/config.py
xdgpspconf/config_io.py
xdgpspconf/errors.py
xdgpspconf/py.typed
xdgpspconf/utils.py
xdgpspconf/xdg.yml
xdgpspconf-1.1.1.dist-info/LICENSE
xdgpspconf-1.1.1.dist-info/METADATA
xdgpspconf-1.1.1.dist-info/WHEEL
xdgpspconf-1.1.1.dist-info/eager_resources.txt
xdgpspconf-1.1.1.dist-info/entry_points.txt
xdgpspconf-1.1.1.dist-info/top_level.txt
xdgpspconf-1.1.1.dist-info/RECORD
