Metadata-Version: 2.1
Name: xdgpspconf
Version: 1.1.1
Summary: xdgpspconf - XDG Platform Suited Project configuration
Home-page: https://gitlab.com/pradyparanjpe/xdgpspconf.git
Download-URL: 
Author: Pradyumna Paranjape
Author-email: pradyparanjpe@rediffmail.com
Maintainer: 
Maintainer-email: 
License: LGPLv3
Project-URL: Documentation, https://pradyparanjpe.gitlab.io/xdgpspconf
Project-URL: Source_url, https://gitlab.com/pradyparanjpe/xdgpspconf.git
Keywords: xdg,cascading,configuration
Platform: linux
Classifier: Programming Language :: Python
Classifier: Programming Language :: Python :: 3.10
Classifier: Programming Language :: Python :: 3.11
Classifier: Programming Language :: Python :: 3.12
Classifier: License :: OSI Approved :: GNU Lesser General Public License v3 (LGPLv3)
Provides: xdgpspconf
Requires-Python: >=3.10
License-File: LICENSE
Requires-Dist: argcomplete
Requires-Dist: pyjson5
Requires-Dist: pyyaml
Requires-Dist: toml
